{"name":"Sprout Invoices","tagline":"Sprout Invoices for WordPress","body":"# Sprout Invoices\r\n\r\n**Create estimates and invoices within your WordPress site. Accept invoice payments from multiple payment processors.**\r\n\r\n## Description\r\n\r\nOur mission at [Sprout Apps](https://sproutapps.co/) is to build a suite of apps to help small businesses and freelancers work more efficiently by reducing the tedious business tasks associated with client management..._seriously though_, I'm trying to build something awesome that you will love. Thank you for your support.\r\n\r\nSprout Invoices is the cornerstone for Sprout Apps. Helping streamline what could be a very complex workflow of accepting estimates and getting invoices paid; integrating the entire process into your site.\r\n\r\n**[Download the most advanced Estimates and Invoicing plugin!](http://downloads.wordpress.org/plugin/sprout-invoices.zip)**\r\n\r\nSprout Invoices helps streamline the complex workflow of accepting estimates and getting invoices paid.\r\n\r\n**[Fully featured upgrades and add-on marketplace available.](https://sproutapps.co/sprout-invoices/)**\r\n\r\n### Requests\r\n\r\nReceiving estimate requests on your site is simplified with Sprout Invoices. Use the customizable default form or integrate with an existing form built a favorite form builder plugin, e.g. Gravity Forms or Ninja Forms.\r\n\r\n### Estimating\r\n\r\nEstimates are automatically created based on estimate request submissions from your site. Review, update, and send the estimate to your new client without having to depend on communicating via email first.\r\n\r\n\r\n### Invoicing\r\n\r\nInvoices are automatically generated from accepted estimates speeding up the process of getting paid. Sprout Invoices understands deposit payments and doesn't have the same hoops other invoice services require.\r\n\r\n\r\n### Flexibility built in\r\nWhile Sprout Invoices automates many of the tasks to improve workflow the power comes from customization.\r\n\r\n*Custom Estimate and Invoice Templates*\r\nEstimates can be fully customized via a new theme template. If you're familiar with customizing a WordPress theme templates than you can create a custom estimate.\r\n\r\n*Notification Editing*\r\nNotifications can be plain-text or HTML. Editing the entire content of a notification is simple with shortcodes that add dynamic content.\r\n\r\n*Plenty of Payment Methods*\r\nAccept credit cards via Paypal Pro or send them to Paypal for invoice payments. P.O. and checks options are also provided.\r\n\r\n*Hundreds of Hooks*\r\nOver two hundred filters and actions allow you to hook into Sprout Invoices and alter whatever you'd like.\r\n\r\n\r\n### Feature List\r\n\r\nSome people love feature lists:\r\n\r\n* Advanced Estimate and Invoice Admin\r\n* Customizable invoice and estimate templates\r\n* Discounts\r\n* Deposit Payments\r\n* Taxes\r\n* Client records with multiple points of contact\r\n* Nested Line Items\r\n* Pre-defined tasks/line-items\r\n* AJAX throughout to speed up work flow\r\n* A lot more...\r\n* Importing from WP-Invoice, Harvest or Freshbooks\r\n* Time tracking (coming soon)\r\n* Recurring payments (coming soon)\r\n* Payment terms (coming soon)\r\n\r\n\r\n### Installation\r\n\r\n1. Upload plugin folder to the `/wp-content/plugins/` directory\r\n1. Activate the plugin through the 'Plugins' menu in WordPress\r\n\r\n### Frequently Asked Questions\r\n\r\n**Please visit [Sprout Apps](https://sproutapps.co/sprout-invoices/).**\r\n\r\n\r\n### Screenshots\r\n\r\n1. Invoice Template\r\n2. Easy Invoice Management\r\n3. A dashboard with charts and summaries answer the question \"how am I doing?\".\r\n4. Dynamic reports allow for date filtering, sorting, search, and exporting.\r\n5. Common management tasks are sped up by Sprout Invoices utilization of AJAX.\r\n\r\nTODO\r\n\r\n### Changelog\r\n\r\n**1.0**\r\n\r\nWelcome! This is a big update and a big step for us.\r\n\r\n* There's a free version and most like you're using it.\r\n* Import from WP-Invoice, Harvest or Freshbooks.\r\n* TODO: Helpers, coming before this is truly 1.0. (shush! this is really 0.9.8)\r\n* So many bug fixes that make this a legit 1.0 release.\r\n* Admin bar links.\r\n* Better dashboard let you know what's up.\r\n* Remove some unnecess****ary cruft.\r\n\r\n**0.9.2**\r\n\r\n* Admin bar links\r\n* Additional hooks and filters required by submission integration add-on\r\n* Minor updates\r\n\r\n**0.9.1**\r\n\r\n* Line Item UI changes.\r\n* Invoice Style fixes\r\n* Plugin updater conflict.\r\n* Better documentation and linking to site.\r\n\r\n\r\n**0.9**\r\n\r\n* Initial Release\r\n\r\n**0.9.0.1**\r\n\r\n* Remove debugging logs from release branch.\r\n\r\n**Support**\r\n\r\nMore info coming soon.","google":"","note":"Don't delete this file! It's used internally to help with page regeneration."}